LICENSE.md
README.md
setup.cfg
setup.py
adaptive_sampling/__init__.py
adaptive_sampling/units.py
adaptive_sampling.egg-info/PKG-INFO
adaptive_sampling.egg-info/SOURCES.txt
adaptive_sampling.egg-info/dependency_links.txt
adaptive_sampling.egg-info/not-zip-safe
adaptive_sampling.egg-info/requires.txt
adaptive_sampling.egg-info/top_level.txt
adaptive_sampling/colvars/__init__.py
adaptive_sampling/colvars/colvars.py
adaptive_sampling/colvars/path_cv.py
adaptive_sampling/colvars/proton_transfer.py
adaptive_sampling/colvars/utils.py
adaptive_sampling/interface/__init__.py
adaptive_sampling/interface/interfaceMD_2D.py
adaptive_sampling/interface/sampling_data.py
adaptive_sampling/processing_tools/__init__.py
adaptive_sampling/processing_tools/gamd.py
adaptive_sampling/processing_tools/mbar.py
adaptive_sampling/processing_tools/metadynamics.py
adaptive_sampling/processing_tools/thermodynamic_integration.py
adaptive_sampling/processing_tools/utils.py
adaptive_sampling/sampling_tools/__init__.py
adaptive_sampling/sampling_tools/abf.py
adaptive_sampling/sampling_tools/amd.py
adaptive_sampling/sampling_tools/awtmeabf.py
adaptive_sampling/sampling_tools/eabf.py
adaptive_sampling/sampling_tools/enhanced_sampling.py
adaptive_sampling/sampling_tools/feneb.py
adaptive_sampling/sampling_tools/metadynamics.py
adaptive_sampling/sampling_tools/metaeabf.py
adaptive_sampling/sampling_tools/reference.py
adaptive_sampling/sampling_tools/utils.py