Metadata-Version: 2.1
Name: adaptive-sampling
Version: 3.0.1
Summary: Sampling algorithms for molecular transitions
Home-page: https://github.com/ochsenfeld-lab/adaptive_sampling
Download-URL: https://github.com/ochsenfeld-lab/adaptive_sampling/archive/refs/tags/v3.0.0.zip
Author: Andreas Hulm
Author-email: andreas.hulm@cup.uni-muenchen.de
License: MIT
Keywords: computational chemistry,molecular dynamics,free energy,chemical reactions
Classifier: Development Status :: 4 - Beta
Classifier: Environment :: Console
Classifier: License :: OSI Approved :: MIT License
Classifier: Programming Language :: Python :: 3.8
License-File: LICENSE.md
